rocketpy/__init__.py
rocketpy/_encoders.py
rocketpy/tools.py
rocketpy/units.py
rocketpy/utilities.py
rocketpy/control/__init__.py
rocketpy/control/controller.py
rocketpy/environment/__init__.py
rocketpy/environment/environment.py
rocketpy/environment/environment_analysis.py
rocketpy/environment/fetchers.py
rocketpy/environment/tools.py
rocketpy/environment/weather_model_mapping.py
rocketpy/mathutils/__init__.py
rocketpy/mathutils/function.py
rocketpy/mathutils/piecewise_function.py
rocketpy/mathutils/vector_matrix.py
rocketpy/motors/__init__.py
rocketpy/motors/fluid.py
rocketpy/motors/hybrid_motor.py
rocketpy/motors/liquid_motor.py
rocketpy/motors/motor.py
rocketpy/motors/solid_motor.py
rocketpy/motors/tank.py
rocketpy/motors/tank_geometry.py
rocketpy/plots/__init__.py
rocketpy/plots/aero_surface_plots.py
rocketpy/plots/environment_analysis_plots.py
rocketpy/plots/environment_plots.py
rocketpy/plots/flight_plots.py
rocketpy/plots/fluid_plots.py
rocketpy/plots/hybrid_motor_plots.py
rocketpy/plots/liquid_motor_plots.py
rocketpy/plots/monte_carlo_plots.py
rocketpy/plots/motor_plots.py
rocketpy/plots/plot_helpers.py
rocketpy/plots/rocket_plots.py
rocketpy/plots/sensitivity_plots.py
rocketpy/plots/solid_motor_plots.py
rocketpy/plots/tank_geometry_plots.py
rocketpy/plots/tank_plots.py
rocketpy/plots/compare/__init__.py
rocketpy/plots/compare/compare.py
rocketpy/plots/compare/compare_flights.py
rocketpy/prints/__init__.py
rocketpy/prints/aero_surface_prints.py
rocketpy/prints/compare_prints.py
rocketpy/prints/controller_prints.py
rocketpy/prints/environment_analysis_prints.py
rocketpy/prints/environment_prints.py
rocketpy/prints/flight_prints.py
rocketpy/prints/fluid_prints.py
rocketpy/prints/hybrid_motor_prints.py
rocketpy/prints/liquid_motor_prints.py
rocketpy/prints/monte_carlo_prints.py
rocketpy/prints/motor_prints.py
rocketpy/prints/parachute_prints.py
rocketpy/prints/rocket_prints.py
rocketpy/prints/sensitivity_prints.py
rocketpy/prints/sensors_prints.py
rocketpy-1.8.0.dist-info/LICENSE
rocketpy-1.8.0.dist-info/METADATA
rocketpy-1.8.0.dist-info/WHEEL
rocketpy-1.8.0.dist-info/top_level.txt
rocketpy-1.8.0.dist-info/RECORD
