Metadata-Version: 2.2
Name: rocketpy
Version: 1.8.0
Summary: Advanced 6-DOF trajectory simulation for High-Power Rocketry.
Author-email: Giovani Hidalgo Ceotto <ghceotto@gmail.com>
Project-URL: homepage, https://rocketpy.org/
Project-URL: documentation, https://docs.rocketpy.org/
Project-URL: repository, https://github.com/RocketPy-Team/RocketPy
Classifier: Programming Language :: Python :: 3
Classifier: License :: OSI Approved :: MIT License
Classifier: Operating System :: OS Independent
Requires-Python: >=3.9
License-File: LICENSE
Requires-Dist: numpy>=1.13
Requires-Dist: scipy>=1.0
Requires-Dist: matplotlib>=3.0
Requires-Dist: netCDF4>=1.6.4
Requires-Dist: requests
Requires-Dist: pytz
Requires-Dist: simplekml
Requires-Dist: dill
Provides-Extra: tests
Requires-Dist: pytest; extra == "tests"
Requires-Dist: pytest-coverage; extra == "tests"
Requires-Dist: black[jupyter]; extra == "tests"
Requires-Dist: flake8-black; extra == "tests"
Requires-Dist: flake8-pyproject; extra == "tests"
Requires-Dist: pandas; extra == "tests"
Requires-Dist: numericalunits==1.25; extra == "tests"
Requires-Dist: pylint; extra == "tests"
Requires-Dist: isort; extra == "tests"
Provides-Extra: env-analysis
Requires-Dist: windrose>=1.6.8; extra == "env-analysis"
Requires-Dist: timezonefinder; extra == "env-analysis"
Requires-Dist: jsonpickle; extra == "env-analysis"
Requires-Dist: ipython; extra == "env-analysis"
Requires-Dist: ipywidgets>=7.6.3; extra == "env-analysis"
Provides-Extra: monte-carlo
Requires-Dist: imageio; extra == "monte-carlo"
Requires-Dist: statsmodels; extra == "monte-carlo"
Requires-Dist: prettytable; extra == "monte-carlo"
Provides-Extra: all
Requires-Dist: rocketpy[env-analysis]; extra == "all"
Requires-Dist: rocketpy[monte-carlo]; extra == "all"
